odoo8_addon_crm_lead_to_event_registration-8.0.1.2.0-py2.7-nspkg.pth
odoo8_addon_crm_lead_to_event_registration-8.0.1.2.0.dist-info/DESCRIPTION.rst
odoo8_addon_crm_lead_to_event_registration-8.0.1.2.0.dist-info/METADATA
odoo8_addon_crm_lead_to_event_registration-8.0.1.2.0.dist-info/RECORD
odoo8_addon_crm_lead_to_event_registration-8.0.1.2.0.dist-info/WHEEL
odoo8_addon_crm_lead_to_event_registration-8.0.1.2.0.dist-info/metadata.json
odoo8_addon_crm_lead_to_event_registration-8.0.1.2.0.dist-info/namespace_packages.txt
odoo8_addon_crm_lead_to_event_registration-8.0.1.2.0.dist-info/top_level.txt
odoo_addons/crm_lead_to_event_registration/README.rst
odoo_addons/crm_lead_to_event_registration/__init__.py
odoo_addons/crm_lead_to_event_registration/__openerp__.py
odoo_addons/crm_lead_to_event_registration/i18n/es.po
odoo_addons/crm_lead_to_event_registration/images/converting.png
odoo_addons/crm_lead_to_event_registration/images/linked.png
odoo_addons/crm_lead_to_event_registration/images/linking.png
odoo_addons/crm_lead_to_event_registration/images/not_linked.png
odoo_addons/crm_lead_to_event_registration/models/__init__.py
odoo_addons/crm_lead_to_event_registration/models/crm_lead.py
odoo_addons/crm_lead_to_event_registration/static/description/icon.png
odoo_addons/crm_lead_to_event_registration/tests/__init__.py
odoo_addons/crm_lead_to_event_registration/tests/test_crm_lead_to_event_registration.py
odoo_addons/crm_lead_to_event_registration/views/crm_lead_view.xml
odoo_addons/crm_lead_to_event_registration/wizard/__init__.py
odoo_addons/crm_lead_to_event_registration/wizard/crm_lead_event_pick.py
odoo_addons/crm_lead_to_event_registration/wizard/crm_lead_event_pick_view.xml
odoo_addons/crm_lead_to_event_registration/wizard/crm_lead_to_opportunity.py
odoo_addons/crm_lead_to_event_registration/wizard/crm_lead_to_opportunity_view.xml
