Metadata-Version: 2.0
Name: odoo8-addon-crm-lead-to-event-registration
Version: 8.0.1.2.0
Summary: Register a lead directly in an event
Home-page: https://www.antiun.com
Author: Tecnativa, Odoo Community Association (OCA)
Author-email: support@odoo-community.org
License: AGPL-3
Platform: UNKNOWN
Classifier: Programming Language :: Python :: 2.7
Classifier: Framework :: Odoo
Classifier: License :: OSI Approved :: GNU Affero General Public License v3
Requires-Dist: odoo (<9.0a,>=8.0a)
